mobly/controllers/wifi/__init__.py
mobly/controllers/wifi/local_sniffer_device.py
mobly/controllers/wifi/openwrt_device.py
mobly/controllers/wifi/data/testing_rsa
mobly/controllers/wifi/lib/__init__.py
mobly/controllers/wifi/lib/captive_portal_server.py
mobly/controllers/wifi/lib/channel_file_streamer.py
mobly/controllers/wifi/lib/constants.py
mobly/controllers/wifi/lib/device_info_utils.py
mobly/controllers/wifi/lib/dhcp_manager.py
mobly/controllers/wifi/lib/errors.py
mobly/controllers/wifi/lib/file_clipper.py
mobly/controllers/wifi/lib/hostapd_manager.py
mobly/controllers/wifi/lib/iw_utils.py
mobly/controllers/wifi/lib/local_sniffer_manager.py
mobly/controllers/wifi/lib/sniffer_manager.py
mobly/controllers/wifi/lib/sniffer_manager_base.py
mobly/controllers/wifi/lib/ssh.py
mobly/controllers/wifi/lib/utils.py
mobly/controllers/wifi/lib/wifi_configs.py
mobly/controllers/wifi/lib/wifi_manager.py
mobly/controllers/wifi/lib/encryption/__init__.py
mobly/controllers/wifi/lib/encryption/base_encryption_config.py
mobly/controllers/wifi/lib/encryption/open.py
mobly/controllers/wifi/lib/encryption/wep.py
mobly/controllers/wifi/lib/encryption/wpa.py
mobly/controllers/wifi/lib/services/__init__.py
mobly/controllers/wifi/lib/services/system_log_service.py
mobly/controllers/wifi/utils/ip_utils.py
mobly/controllers/wifi/utils/iperf_utils.py
mobly/controllers/wifi/utils/veth_utils.py
mobly_wifi-1.3.0.dist-info/licenses/LICENSE
mobly_wifi-1.3.0.dist-info/METADATA
mobly_wifi-1.3.0.dist-info/WHEEL
mobly_wifi-1.3.0.dist-info/top_level.txt
mobly_wifi-1.3.0.dist-info/RECORD
