Metadata-Version: 2.4
Name: mobly-wifi
Version: 1.3.0
Summary: Mobly WiFi controller module for using Python code to operate network devices in Mobly tests.
Home-page: https://github.com/google/mobly-wifi
Author: Google Inc.
Author-email: minghaoli@google.com
Maintainer-email: Minghao Li <minghaoli@google.com>
License: 
Requires-Python: >=3.11
License-File: LICENSE
Requires-Dist: mobly>=1.12.2
Requires-Dist: immutabledict
Requires-Dist: paramiko>=2.10.4
Requires-Dist: pyzmq>=15.0.0
Requires-Dist: packaging
Dynamic: author-email
Dynamic: home-page
Dynamic: license-file
Dynamic: requires-python
